{
  "data": {
    "endRow": 6,
    "hasNextPage": false,
    "hasPreviousPage": false,
    "isFirstPage": true,
    "isLastPage": true,
    "list": [
      {
        "activityProductList": [],
        "applicantForm": "",
        "applicantsLimit": 0,
        "audioCount": 5,
        "brief": "",
        "btId": 0,
        "canBuyLevel": "1,100,110,120,130,140,200,210,220,",
        "courseAudioVoList": [
          {
          "courseId":594,
          "detail":"",
          "duration":155,
          "durationDesc":"02:35",
          "goodsName":"如何玩转全球自选app",
          "goodsPicUrl":"https://img.mall.xc2018.com.cn/mall/upload/20190626/161626_46_5e81.jpg",
          "id":2006,
          "isFree":true,
          "learningProgress":0,
          "name":"第一节：一分钟玩转全球自选app",
          "url":"https://img.mall.xc2018.com.cn/mall/upload/20190626/170746_91_s9ic.mp4"
        },
          {
            "courseId":594,
            "detail":"",
            "duration":135,
            "durationDesc":"02:15",
            "goodsName":"如何玩转全球自选app",
            "goodsPicUrl":"https://img.mall.xc2018.com.cn/mall/upload/20190626/161626_46_5e81.jpg",
            "id":2007,
            "isFree":true,
            "learningProgress":0,
            "name":"第二节：如何成为全球自选会员，开启创业之旅",
            "url":"https://img.mall.xc2018.com.cn/mall/upload/20190626/171012_51_pbeo.mp4"
          },
          {
            "courseId":594,
            "detail":"",
            "duration":277,
            "durationDesc":"04:37",
            "goodsName":"如何玩转全球自选app",
            "goodsPicUrl":"https://img.mall.xc2018.com.cn/mall/upload/20190626/161626_46_5e81.jpg",
            "id":2008,
            "isFree":true,
            "learningProgress":0,
            "name":"第三节：全球自选五大功能介绍",
            "url":"https://img.mall.xc2018.com.cn/mall/upload/20190626/171404_7_w2pk.mp4"
          },
          {
            "courseId":594,
            "detail":"",
            "duration":121,
            "durationDesc":"02:01",
            "goodsName":"如何玩转全球自选app",
            "goodsPicUrl":"https://img.mall.xc2018.com.cn/mall/upload/20190626/161626_46_5e81.jpg",
            "id":2009,
            "isFree":true,
            "learningProgress":0,
            "name":"第四节：全球自选赚钱小指南",
            "url":"https://img.mall.xc2018.com.cn/mall/upload/20190626/171511_40_pqa6.mp4"
          },
          {
            "courseId":594,
            "detail":"",
            "duration":110,
            "durationDesc":"01:50",
            "goodsName":"如何玩转全球自选app",
            "goodsPicUrl":"https://img.mall.xc2018.com.cn/mall/upload/20190626/161626_46_5e81.jpg",
            "id":2010,
            "isFree":true,
            "learningProgress":0,
            "name":"第五节：全球自选售后小课堂",
            "url":"https://img.mall.xc2018.com.cn/mall/upload/20190626/171515_29_24sg.mp4"
          }],
        "courseType": 2,
        "detail": "<p><img src=\"https://img.mall.xc2018.com.cn/mall/upload/20190626/161751_8_ylj3.jpeg\"><img src=\"https://img.mall.xc2018.com.cn/mall/upload/20190626/171230_24_0c8q.jpg\"></p>",
        "errorType": 0,
        "freeLevel": "",
        "gallery": "[{\"name\":\"img0\",\"url\":\"https://img.mall.xc2018.com.cn/mall/upload/20190626/161630_58_rrbe.jpg\",\"img\":\"https://img.mall.xc2018.com.cn/mall/upload/20190626/161630_58_rrbe.jpg\",\"uid\":1561542492435,\"status\":\"success\"}]",
        "hasQuestion": false,
        "id": 954,
        "isBuy": false,
        "isCanBuy": false,
        "isFree": false,
        "isHot": false,
        "isListen": 0,
        "isNaturalPerson": false,
        "isNew": false,
        "isOnlinePay": true,
        "isPayAfter": false,
        "isPaymentAgreement": false,
        "isVipCanBuy": true,
        "isVipFree": false,
        "listenCount": 36,
        "listenCountDesc": "已有36人学习",
        "name": "如何玩转全球自选app",
        "onSaleEndTime": 0,
        "onSaleEndTimeDesc": "",
        "onSaleStartTime": 0,
        "onSaleStartTimeDesc": "",
        "onSaleType": 1,
        "payAfterPic": "",
        "payAfterUrl": "",
        "payWay": 0,
        "payWayItemList": [],
        "picUrl": "https://img.mall.xc2018.com.cn/mall/upload/20190626/161626_46_5e81.jpg",
        "priceTag": 0,
        "productId": 594,
        "productQuantity": 0,
        "productType": 2,
        "questionVVo": null,
        "retailPrice": 0,
        "retailPriceDesc": "0.00",
        "salesNumber": 0,
        "salesNumberDesc": "已有0人学习",
        "showPrice": 0,
        "showPriceDesc": "0.00",
        "skuPriceRange": "",
        "skuVipPriceRange": "",
        "tag": "",
        "tagName": "",
        "vipPrice": 0,
        "vipPriceDesc": "0.00"
      },
      {
        "activityProductList": [],
        "applicantForm": "",
        "applicantsLimit": 0,
        "audioCount": 2,
        "brief": "",
        "btId": 0,
        "canBuyLevel": "1,100,110,120,130,140,200,210,220,",
        "courseAudioVoList": [
          {
          "courseId":572,
          "detail":"",
          "duration":213,
          "durationDesc":"03:33",
          "goodsName":"微信昵称头像个性签名如何设置",
          "goodsPicUrl":"https://img.mall.xc2018.com.cn/mall/upload/20190625/175020_23_lvvq.jpg",
          "id":1701,
          "isFree":true,
          "learningProgress":0,
          "name":"第一节：如何塑造第一印象之头像和呢称塑造",
          "url":"https://img.mall.xc2018.com.cn/mall/upload/20190625/175054_29_ed55.mp4"
        },
          {
            "courseId":572,
            "detail":"",
            "duration":77,
            "durationDesc":"01:17",
            "goodsName":"微信昵称头像个性签名如何设置",
            "goodsPicUrl":"https://img.mall.xc2018.com.cn/mall/upload/20190625/175020_23_lvvq.jpg",
            "id":1702,
            "isFree":true,
            "learningProgress":0,
            "name":"第二节：如何塑造第一印象之背景和签名塑造",
            "url":"https://img.mall.xc2018.com.cn/mall/upload/20190625/175108_31_rrhs.mp4"
          }],
        "courseType": 2,
        "detail": "<p><img src=\"https://img.mall.xc2018.com.cn/mall/upload/20190625/174900_65_8vc4.jpeg\"><img src=\"https://img.mall.xc2018.com.cn/mall/upload/20190625/174915_74_f2d0.jpg\"></p>",
        "errorType": 0,
        "freeLevel": "200,210,220,",
        "gallery": "[{\"name\":\"img0\",\"url\":\"https://img.mall.xc2018.com.cn/mall/upload/20190625/175026_50_z5bg.jpg\",\"img\":\"https://img.mall.xc2018.com.cn/mall/upload/20190625/175026_50_z5bg.jpg\",\"uid\":1561542547673,\"status\":\"success\"}]",
        "hasQuestion": false,
        "id": 932,
        "isBuy": false,
        "isCanBuy": false,
        "isFree": false,
        "isHot": false,
        "isListen": 0,
        "isNaturalPerson": false,
        "isNew": false,
        "isOnlinePay": true,
        "isPayAfter": false,
        "isPaymentAgreement": false,
        "isVipCanBuy": true,
        "isVipFree": false,
        "listenCount": 53,
        "listenCountDesc": "已有53人学习",
        "name": "微信昵称头像个性签名如何设置",
        "onSaleEndTime": 0,
        "onSaleEndTimeDesc": "",
        "onSaleStartTime": 0,
        "onSaleStartTimeDesc": "",
        "onSaleType": 1,
        "payAfterPic": "",
        "payAfterUrl": "",
        "payWay": 0,
        "payWayItemList": [],
        "picUrl": "https://img.mall.xc2018.com.cn/mall/upload/20190625/175020_23_lvvq.jpg",
        "priceTag": 0,
        "productId": 572,
        "productQuantity": 0,
        "productType": 2,
        "questionVVo": null,
        "retailPrice": 0,
        "retailPriceDesc": "0.00",
        "salesNumber": 0,
        "salesNumberDesc": "已有0人学习",
        "showPrice": 0,
        "showPriceDesc": "0.00",
        "skuPriceRange": "",
        "skuVipPriceRange": "",
        "tag": "",
        "tagName": "",
        "vipPrice": 0,
        "vipPriceDesc": "0.00"
      },
      {
        "activityProductList": [],
        "applicantForm": "",
        "applicantsLimit": 0,
        "audioCount": 1,
        "brief": "",
        "btId": 0,
        "canBuyLevel": "1,100,110,120,130,140,200,210,220,",
        "courseAudioVoList": [
          {
          "courseId":574,
          "detail":"",
          "duration":347,
          "durationDesc":"05:47",
          "goodsName":"新手小白如何开启第一单",
          "goodsPicUrl":"https://img.mall.xc2018.com.cn/mall/upload/20190626/113230_30_xu5x.jpg",
          "id":1711,
          "isFree":true,
          "learningProgress":0,
          "name":"第一节：新手小白如何开启第一单",
          "url":"https://img.mall.xc2018.com.cn/mall/upload/20190626/112958_20_3jnw.mp4"
        }],
        "courseType": 2,
        "detail": "<p><img src=\"https://img.mall.xc2018.com.cn/mall/upload/20190626/112917_55_bln7.jpeg\"><img src=\"https://img.mall.xc2018.com.cn/mall/upload/20190626/112926_93_z4yv.jpg\"></p>",
        "errorType": 0,
        "freeLevel": "",
        "gallery": "[{\"name\":\"img0\",\"url\":\"https://img.mall.xc2018.com.cn/mall/upload/20190626/113233_87_m8kw.jpg\",\"img\":\"https://img.mall.xc2018.com.cn/mall/upload/20190626/113233_87_m8kw.jpg\",\"uid\":1561542562148,\"status\":\"success\"}]",
        "hasQuestion": false,
        "id": 934,
        "isBuy": false,
        "isCanBuy": false,
        "isFree": false,
        "isHot": false,
        "isListen": 0,
        "isNaturalPerson": false,
        "isNew": false,
        "isOnlinePay": true,
        "isPayAfter": false,
        "isPaymentAgreement": false,
        "isVipCanBuy": true,
        "isVipFree": false,
        "listenCount": 36,
        "listenCountDesc": "已有36人学习",
        "name": "新手小白如何开启第一单",
        "onSaleEndTime": 0,
        "onSaleEndTimeDesc": "",
        "onSaleStartTime": 0,
        "onSaleStartTimeDesc": "",
        "onSaleType": 1,
        "payAfterPic": "",
        "payAfterUrl": "",
        "payWay": 0,
        "payWayItemList": [],
        "picUrl": "https://img.mall.xc2018.com.cn/mall/upload/20190626/113230_30_xu5x.jpg",
        "priceTag": 0,
        "productId": 574,
        "productQuantity": 0,
        "productType": 2,
        "questionVVo": null,
        "retailPrice": 0,
        "retailPriceDesc": "0.00",
        "salesNumber": 0,
        "salesNumberDesc": "已有0人学习",
        "showPrice": 0,
        "showPriceDesc": "0.00",
        "skuPriceRange": "",
        "skuVipPriceRange": "",
        "tag": "",
        "tagName": "",
        "vipPrice": 0,
        "vipPriceDesc": "0.00"
      },
      {
        "activityProductList": [],
        "applicantForm": "",
        "applicantsLimit": 0,
        "audioCount": 3,
        "brief": "",
        "btId": 0,
        "canBuyLevel": "1,100,110,120,130,140,200,210,220,",
        "courseAudioVoList": [
          {
          "courseId":573,
          "detail":"",
          "duration":269,
          "durationDesc":"04:29",
          "goodsName":"地推吸粉3部曲",
          "goodsPicUrl":"https://img.mall.xc2018.com.cn/mall/upload/20190626/115928_2_czqq.jpg",
          "id":1703,
          "isFree":true,
          "learningProgress":0,
          "name":"第一节：地推的前期准备工作",
          "url":"https://img.mall.xc2018.com.cn/mall/upload/20190625/180948_6_p1fv.mp4"
        },
          {
            "courseId":573,
            "detail":"",
            "duration":163,
            "durationDesc":"02:43",
            "goodsName":"地推吸粉3部曲",
            "goodsPicUrl":"https://img.mall.xc2018.com.cn/mall/upload/20190626/115928_2_czqq.jpg",
            "id":1704,
            "isFree":true,
            "learningProgress":0,
            "name":"第二节：地推操作实施4大方法",
            "url":"https://img.mall.xc2018.com.cn/mall/upload/20190625/181030_10_mdu4.mp4"
          },
          {
            "courseId":573,
            "detail":"",
            "duration":166,
            "durationDesc":"02:46",
            "goodsName":"地推吸粉3部曲",
            "goodsPicUrl":"https://img.mall.xc2018.com.cn/mall/upload/20190626/115928_2_czqq.jpg",
            "id":1705,
            "isFree":true,
            "learningProgress":0,
            "name":"第三节：地推后如何维护",
            "url":"https://img.mall.xc2018.com.cn/mall/upload/20190625/181050_33_616f.mp4"
          }],
        "courseType": 2,
        "detail": "<p><img src=\"https://img.mall.xc2018.com.cn/mall/upload/20190625/180527_32_pj1a.jpeg\"><img src=\"https://img.mall.xc2018.com.cn/mall/upload/20190625/180538_22_617w.jpg\"></p>",
        "errorType": 0,
        "freeLevel": "200,210,220,",
        "gallery": "[{\"name\":\"img0\",\"url\":\"https://img.mall.xc2018.com.cn/mall/upload/20190625/180801_92_xqyn.jpg\",\"img\":\"https://img.mall.xc2018.com.cn/mall/upload/20190625/180801_92_xqyn.jpg\",\"uid\":1561521511296,\"status\":\"success\"}]",
        "hasQuestion": false,
        "id": 933,
        "isBuy": false,
        "isCanBuy": false,
        "isFree": false,
        "isHot": false,
        "isListen": 0,
        "isNaturalPerson": false,
        "isNew": false,
        "isOnlinePay": true,
        "isPayAfter": false,
        "isPaymentAgreement": false,
        "isVipCanBuy": true,
        "isVipFree": false,
        "listenCount": 40,
        "listenCountDesc": "已有40人学习",
        "name": "地推吸粉3部曲",
        "onSaleEndTime": 0,
        "onSaleEndTimeDesc": "",
        "onSaleStartTime": 0,
        "onSaleStartTimeDesc": "",
        "onSaleType": 1,
        "payAfterPic": "",
        "payAfterUrl": "",
        "payWay": 0,
        "payWayItemList": [],
        "picUrl": "https://img.mall.xc2018.com.cn/mall/upload/20190626/115928_2_czqq.jpg",
        "priceTag": 0,
        "productId": 573,
        "productQuantity": 0,
        "productType": 2,
        "questionVVo": null,
        "retailPrice": 0,
        "retailPriceDesc": "0.00",
        "salesNumber": 4,
        "salesNumberDesc": "已有4人学习",
        "showPrice": 0,
        "showPriceDesc": "0.00",
        "skuPriceRange": "",
        "skuVipPriceRange": "",
        "tag": "",
        "tagName": "",
        "vipPrice": 0,
        "vipPriceDesc": "0.00"
      },
      {
        "activityProductList": [],
        "applicantForm": "",
        "applicantsLimit": 0,
        "audioCount": 2,
        "brief": "",
        "btId": 0,
        "canBuyLevel": "1,100,110,120,130,140,200,210,220,",
        "courseAudioVoList": [
          {
          "courseId":591,
          "detail":"",
          "duration":300,
          "durationDesc":"05:00",
          "goodsName":"线下沙龙系列",
          "goodsPicUrl":"https://img.mall.xc2018.com.cn/mall/upload/20190626/151047_18_ce7z.jpg",
          "id":1995,
          "isFree":true,
          "learningProgress":0,
          "name":"第一节：如何办好一场沙龙会",
          "url":"https://img.mall.xc2018.com.cn/mall/upload/20190626/151305_97_hryp.mp4"
        },
          {
            "courseId":591,
            "detail":"",
            "duration":107,
            "durationDesc":"01:47",
            "goodsName":"线下沙龙系列",
            "goodsPicUrl":"https://img.mall.xc2018.com.cn/mall/upload/20190626/151047_18_ce7z.jpg",
            "id":1996,
            "isFree":true,
            "learningProgress":0,
            "name":"第二节：沙龙会结束后你该怎么做",
            "url":"https://img.mall.xc2018.com.cn/mall/upload/20190626/151209_96_rvxf.mp4"
          }],
        "courseType": 2,
        "detail": "<p><img src=\"https://img.mall.xc2018.com.cn/mall/upload/20190626/151107_62_7gzt.jpeg\"><img src=\"https://img.mall.xc2018.com.cn/mall/upload/20190626/151120_76_3i75.jpg\"></p>",
        "errorType": 0,
        "freeLevel": "",
        "gallery": "[{\"name\":\"img0\",\"url\":\"https://img.mall.xc2018.com.cn/mall/upload/20190626/151051_84_hdns.jpg\",\"img\":\"https://img.mall.xc2018.com.cn/mall/upload/20190626/151051_84_hdns.jpg\",\"uid\":1561533315504,\"status\":\"success\"}]",
        "hasQuestion": false,
        "id": 951,
        "isBuy": false,
        "isCanBuy": false,
        "isFree": false,
        "isHot": false,
        "isListen": 0,
        "isNaturalPerson": false,
        "isNew": false,
        "isOnlinePay": true,
        "isPayAfter": false,
        "isPaymentAgreement": false,
        "isVipCanBuy": true,
        "isVipFree": false,
        "listenCount": 5,
        "listenCountDesc": "已有5人学习",
        "name": "线下沙龙系列",
        "onSaleEndTime": 0,
        "onSaleEndTimeDesc": "",
        "onSaleStartTime": 0,
        "onSaleStartTimeDesc": "",
        "onSaleType": 1,
        "payAfterPic": "",
        "payAfterUrl": "",
        "payWay": 0,
        "payWayItemList": [],
        "picUrl": "https://img.mall.xc2018.com.cn/mall/upload/20190626/151047_18_ce7z.jpg",
        "priceTag": 0,
        "productId": 591,
        "productQuantity": 0,
        "productType": 2,
        "questionVVo": null,
        "retailPrice": 0,
        "retailPriceDesc": "0.00",
        "salesNumber": 0,
        "salesNumberDesc": "已有0人学习",
        "showPrice": 0,
        "showPriceDesc": "0.00",
        "skuPriceRange": "",
        "skuVipPriceRange": "",
        "tag": "",
        "tagName": "",
        "vipPrice": 0,
        "vipPriceDesc": "0.00"
      },
      {
        "activityProductList": [],
        "applicantForm": "",
        "applicantsLimit": 0,
        "audioCount": 1,
        "brief": "",
        "btId": 0,
        "canBuyLevel": "1,100,110,120,130,140,200,210,220,",
        "courseAudioVoList": [
          {
          "courseId":585,
          "detail":"",
          "duration":368,
          "durationDesc":"06:08",
          "goodsName":"如何搭建你的社群",
          "goodsPicUrl":"https://img.mall.xc2018.com.cn/mall/upload/20190626/140158_71_i98u.jpg",
          "id":1970,
          "isFree":true,
          "learningProgress":0,
          "name":"如何搭建你的社群",
          "url":"https://img.mall.xc2018.com.cn/mall/upload/20190626/140313_68_denw.mp4"
        }],
        "courseType": 2,
        "detail": "<p><img src=\"https://img.mall.xc2018.com.cn/mall/upload/20190626/140225_28_crob.jpeg\"><img src=\"https://img.mall.xc2018.com.cn/mall/upload/20190626/140236_57_zawi.jpg\"></p>",
        "errorType": 0,
        "freeLevel": "",
        "gallery": "[{\"img\":\"https://img.mall.xc2018.com.cn/mall/upload/20190626/140203_31_74op.jpg\"}]",
        "hasQuestion": false,
        "id": 945,
        "isBuy": false,
        "isCanBuy": false,
        "isFree": false,
        "isHot": false,
        "isListen": 0,
        "isNaturalPerson": false,
        "isNew": false,
        "isOnlinePay": true,
        "isPayAfter": false,
        "isPaymentAgreement": false,
        "isVipCanBuy": true,
        "isVipFree": false,
        "listenCount": 9,
        "listenCountDesc": "已有9人学习",
        "name": "如何搭建你的社群",
        "onSaleEndTime": 0,
        "onSaleEndTimeDesc": "",
        "onSaleStartTime": 0,
        "onSaleStartTimeDesc": "",
        "onSaleType": 1,
        "payAfterPic": "",
        "payAfterUrl": "",
        "payWay": 0,
        "payWayItemList": [],
        "picUrl": "https://img.mall.xc2018.com.cn/mall/upload/20190626/140158_71_i98u.jpg",
        "priceTag": 0,
        "productId": 585,
        "productQuantity": 0,
        "productType": 2,
        "questionVVo": null,
        "retailPrice": 0,
        "retailPriceDesc": "0.00",
        "salesNumber": 0,
        "salesNumberDesc": "已有0人学习",
        "showPrice": 0,
        "showPriceDesc": "0.00",
        "skuPriceRange": "",
        "skuVipPriceRange": "",
        "tag": "",
        "tagName": "",
        "vipPrice": 0,
        "vipPriceDesc": "0.00"
      },
      {
        "activityProductList": [],
        "applicantForm": "",
        "applicantsLimit": 0,
        "audioCount": 2,
        "brief": "",
        "btId": 0,
        "canBuyLevel": "1,100,110,120,130,140,200,210,220,",
        "courseAudioVoList": [
          {
          "courseId":575,
          "detail":"",
          "duration":207,
          "durationDesc":"03:27",
          "goodsName":"一对一沟通技巧",
          "goodsPicUrl":"https://img.mall.xc2018.com.cn/mall/upload/20190626/114550_77_fvb0.jpg",
          "id":1712,
          "isFree":true,
          "learningProgress":0,
          "name":"第一节：了解对方，挖掘痛点",
          "url":"https://img.mall.xc2018.com.cn/mall/upload/20190626/114743_44_gxgz.mp4"
        },
          {
            "courseId":575,
            "detail":"",
            "duration":308,
            "durationDesc":"05:08",
            "goodsName":"一对一沟通技巧",
            "goodsPicUrl":"https://img.mall.xc2018.com.cn/mall/upload/20190626/114550_77_fvb0.jpg",
            "id":1713,
            "isFree":true,
            "learningProgress":0,
            "name":"第二节：沟通的5个技巧",
            "url":"https://img.mall.xc2018.com.cn/mall/upload/20190626/114807_51_51fp.mp4"
          }],
        "courseType": 2,
        "detail": "<p><img src=\"https://img.mall.xc2018.com.cn/mall/upload/20190626/114634_56_ip0n.jpeg\"><img src=\"https://img.mall.xc2018.com.cn/mall/upload/20190626/114645_15_h85w.jpg\"></p>",
        "errorType": 0,
        "freeLevel": "",
        "gallery": "[{\"img\":\"https://img.mall.xc2018.com.cn/mall/upload/20190626/114618_63_jl6l.jpg\"}]",
        "hasQuestion": false,
        "id": 935,
        "isBuy": false,
        "isCanBuy": false,
        "isFree": false,
        "isHot": false,
        "isListen": 0,
        "isNaturalPerson": false,
        "isNew": false,
        "isOnlinePay": true,
        "isPayAfter": false,
        "isPaymentAgreement": false,
        "isVipCanBuy": true,
        "isVipFree": false,
        "listenCount": 15,
        "listenCountDesc": "已有15人学习",
        "name": "一对一沟通技巧",
        "onSaleEndTime": 0,
        "onSaleEndTimeDesc": "",
        "onSaleStartTime": 0,
        "onSaleStartTimeDesc": "",
        "onSaleType": 1,
        "payAfterPic": "",
        "payAfterUrl": "",
        "payWay": 0,
        "payWayItemList": [],
        "picUrl": "https://img.mall.xc2018.com.cn/mall/upload/20190626/114550_77_fvb0.jpg",
        "priceTag": 0,
        "productId": 575,
        "productQuantity": 0,
        "productType": 2,
        "questionVVo": null,
        "retailPrice": 0,
        "retailPriceDesc": "0.00",
        "salesNumber": 0,
        "salesNumberDesc": "已有0人学习",
        "showPrice": 0,
        "showPriceDesc": "0.00",
        "skuPriceRange": "",
        "skuVipPriceRange": "",
        "tag": "",
        "tagName": "",
        "vipPrice": 0,
        "vipPriceDesc": "0.00"
      }
    ],
    "navigateFirstPage": 1,
    "navigateLastPage": 1,
    "navigatePages": 8,
    "navigatepageNums": [
      1
    ],
    "nextPage": 0,
    "pageNum": 1,
    "pageSize": 7,
    "pages": 1,
    "prePage": 0,
    "size": 7,
    "startRow": 0,
    "total": 7
  },
  "errmsg": "success",
  "errno": 0
}
